mwaa_env_var_plugin/__init__.py
mwaa_env_var_plugin/test_plugin.py
mwaa_env_var_plugin-1.0.1.dist-info/LICENSE
mwaa_env_var_plugin-1.0.1.dist-info/METADATA
mwaa_env_var_plugin-1.0.1.dist-info/WHEEL
mwaa_env_var_plugin-1.0.1.dist-info/entry_points.txt
mwaa_env_var_plugin-1.0.1.dist-info/top_level.txt
mwaa_env_var_plugin-1.0.1.dist-info/RECORD
