Metadata-Version: 2.1
Name: mwaa-env-var-plugin
Version: 1.0.1
Summary: Environment variable plugin for MWAA
Home-page: https://github.com/maslick/mwaa_env_var_plugin
Author: Pavel Maslov
License: MIT
Platform: Linux
Platform: Windows
Platform: MacOS
License-File: LICENSE
